Workbook
Name Slicer_Country: #N/A
Name Slicer_Discount_Band: #N/A
Name Slicer_Product: #N/A
Name Slicer_Segment: #N/A
Name Slicer_Year: #N/A

Sheet Raw Data
A1: Segment | B1: Country | C1: Product | D1: Discount Band | E1: Units Sold | F1: Manufacturing Price | G1: Sale Price | H1: Gross Sales | I1: Discounts | J1: Sales | K1: COGS | L1: Profit | M1: Date | N1: Month Number | O1: Month Name | P1: Year
A2: Government | B2: Canada | C2: Carretera | D2: None | E2: 1618.5 | F2: 3 | G2: 20 | H2: 32370 | I2: $- | J2: 32370 | K2: 16185 | L2: $16,185.00 | M2: 41640 | N2: 1 | O2: January | P2: 2014
A3: Government | B3: Germany | C3: Carretera | D3: None | E3: 1321 | F3: 3 | G3: 20 | H3: 26420 | I3: $- | J3: 26420 | K3: 13210 | L3: $13,210.00 | M3: 41640 | N3: 1 | O3: January | P3: 2014
A4: Midmarket | B4: France | C4: Carretera | D4: None | E4: 2178 | F4: 3 | G4: 15 | H4: 32670 | I4: $- | J4: 32670 | K4: 21780 | L4: $10,890.00 | M4: 41791 | N4: 6 | O4: June | P4: 2014
A5: Midmarket | B5: Germany | C5: Carretera | D5: None | E5: 888 | F5: 3 | G5: 15 | H5: 13320 | I5: $- | J5: 13320 | K5: 8880 | L5: $4,440.00 | M5: 41791 | N5: 6 | O5: June | P5: 2014
A6: Midmarket | B6: Mexico | C6: Carretera | D6: None | E6: 2470 | F6: 3 | G6: 15 | H6: 37050 | I6: $- | J6: 37050 | K6: 24700 | L6: $12,350.00 | M6: 41791 | N6: 6 | O6: June | P6: 2014
A7: Government | B7: Germany | C7: Carretera | D7: None | E7: 1513 | F7: 3 | G7: 350 | H7: 529550 | I7: $- | J7: 529550 | K7: 393380 | L7: $136,170.00 | M7: 41974 | N7: 12 | O7: December | P7: 2014
A8: Midmarket | B8: Germany | C8: Montana | D8: None | E8: 921 | F8: 5 | G8: 15 | H8: 13815 | I8: $- | J8: 13815 | K8: 9210 | L8: $4,605.00 | M8: 41699 | N8: 3 | O8: March | P8: 2014
A9: Channel Partners | B9: Canada | C9: Montana | D9: None | E9: 2518 | F9: 5 | G9: 12 | H9: 30216 | I9: $- | J9: 30216 | K9: 7554 | L9: $22,662.00 | M9: 41791 | N9: 6 | O9: June | P9: 2014
A10: Government | B10: France | C10: Montana | D10: None | E10: 1899 | F10: 5 | G10: 20 | H10: 37980 | I10: $- | J10: 37980 | K10: 18990 | L10: $18,990.00 | M10: 41791 | N10: 6 | O10: June | P10: 2014
A11: Channel Partners | B11: Germany | C11: Montana | D11: None | E11: 1545 | F11: 5 | G11: 12 | H11: 18540 | I11: $- | J11: 18540 | K11: 4635 | L11: $13,905.00 | M11: 41791 | N11: 6 | O11: June | P11: 2014
A12: Midmarket | B12: Mexico | C12: Montana | D12: None | E12: 2470 | F12: 5 | G12: 15 | H12: 37050 | I12: $- | J12: 37050 | K12: 24700 | L12: $12,350.00 | M12: 41791 | N12: 6 | O12: June | P12: 2014
A13: Enterprise | B13: Canada | C13: Montana | D13: None | E13: 2665.5 | F13: 5 | G13: 125 | H13: 333187.5 | I13: $- | J13: 333187.5 | K13: 319860 | L13: $13,327.50 | M13: 41821 | N13: 7 | O13: July | P13: 2014
... A701: Channel Partners | B701: United States of America | C701: VTT | D701: High | E701: 1806 | F701: 250 | G701: 12 | H701: 21672 | I701: $3,250.80 | J701: 18421.2 | K701: 5418 | L701: $13,003.20 | M701: 41760 | N701: 5 | O701: May | P701: 2014

Sheet financial_data
A1: Segment | B1: Country | C1: Product | D1: Discount Band | E1: Units Sold | F1: Manufacturing Price | G1: Sale Price | H1: Gross Sales | I1: Discounts | J1: Sales | K1: COGS | L1: Profit | M1: Date | N1: Month Number | O1: Month Name | P1: Year | Q1: Profit margin | R1: Sales Category | S1: Error check | T1: month-year | U1: Profit Status | V1: Sales Size | W1: ISDate
A2: Government | B2: Canada | C2: Carretera | D2: None | E2: 1618.5 | F2: 3 | G2: 20 | H2: 32370 | I2: 0 | J2: 32370 | K2: 16185 | L2: 16185 | M2: 41640 | N2: 1 | O2: January | P2: 2014 | Q2: =New_Finance_Data[[#This Row],[ Profit ]]/New_Finance_Data[[#This Row],[ Sales ]] -> 0.5 | R2: =IF(New_Finance_Data[[#This Row],[ Sales ]]>=100000,"High",IF(New_Finance_Data[[#This Row],[ Sales ]]>=50000,"Medium","Low")) -> Low | S2: =IF(OR(ISBLANK(New_Finance_Data[[#This Row],[ Sales ]]),ISBLANK(New_Finance_Data[[#This Row],[ Profit ]])),"Missing","OK") -> OK | T2: =TEXT(New_Finance_Data[[#This Row],[Date]],"MMM-YYYY") -> Jan-2014 | U2: =IF(New_Finance_Data[[#This Row],[ Profit ]]>0,"Profit","Loss") -> Profit | V2: =IF(New_Finance_Data[[#This Row],[ Sales ]]>=50000,"High Sales","Low Sales") -> Low Sales | W2: =ISNUMBER(New_Finance_Data[[#This Row],[Date]]) -> TRUE
A3: Government | B3: Germany | C3: Carretera | D3: None | E3: 1321 | F3: 3 | G3: 20 | H3: 26420 | I3: 0 | J3: 26420 | K3: 13210 | L3: 13210 | M3: 41640 | N3: 1 | O3: January | P3: 2014 | Q3: =New_Finance_Data[[#This Row],[ Profit ]]/New_Finance_Data[[#This Row],[ Sales ]] -> 0.5 | R3: =IF(New_Finance_Data[[#This Row],[ Sales ]]>=100000,"High",IF(New_Finance_Data[[#This Row],[ Sales ]]>=50000,"Medium","Low")) -> Low | S3: =IF(OR(ISBLANK(New_Finance_Data[[#This Row],[ Sales ]]),ISBLANK(New_Finance_Data[[#This Row],[ Profit ]])),"Missing","OK") -> OK | T3: =TEXT(New_Finance_Data[[#This Row],[Date]],"MMM-YYYY") -> Jan-2014 | U3: =IF(New_Finance_Data[[#This Row],[ Profit ]]>0,"Profit","Loss") -> Profit | V3: =IF(New_Finance_Data[[#This Row],[ Sales ]]>=50000,"High Sales","Low Sales") -> Low Sales | W3: =ISNUMBER(New_Finance_Data[[#This Row],[Date]]) -> TRUE
A4: Midmarket | B4: France | C4: Carretera | D4: None | E4: 2178 | F4: 3 | G4: 15 | H4: 32670 | I4: 0 | J4: 32670 | K4: 21780 | L4: 10890 | M4: 41791 | N4: 6 | O4: June | P4: 2014 | Q4: =New_Finance_Data[[#This Row],[ Profit ]]/New_Finance_Data[[#This Row],[ Sales ]] -> 0.33333333 | R4: =IF(New_Finance_Data[[#This Row],[ Sales ]]>=100000,"High",IF(New_Finance_Data[[#This Row],[ Sales ]]>=50000,"Medium","Low")) -> Low | S4: =IF(OR(ISBLANK(New_Finance_Data[[#This Row],[ Sales ]]),ISBLANK(New_Finance_Data[[#This Row],[ Profit ]])),"Missing","OK") -> OK | T4: =TEXT(New_Finance_Data[[#This Row],[Date]],"MMM-YYYY") -> Jun-2014 | U4: =IF(New_Finance_Data[[#This Row],[ Profit ]]>0,"Profit","Loss") -> Profit | V4: =IF(New_Finance_Data[[#This Row],[ Sales ]]>=50000,"High Sales","Low Sales") -> Low Sales | W4: =ISNUMBER(New_Finance_Data[[#This Row],[Date]]) -> TRUE
A5: Midmarket | B5: Germany | C5: Carretera | D5: None | E5: 888 | F5: 3 | G5: 15 | H5: 13320 | I5: 0 | J5: 13320 | K5: 8880 | L5: 4440 | M5: 41791 | N5: 6 | O5: June | P5: 2014 | Q5: =New_Finance_Data[[#This Row],[ Profit ]]/New_Finance_Data[[#This Row],[ Sales ]] -> 0.33333333 | R5: =IF(New_Finance_Data[[#This Row],[ Sales ]]>=100000,"High",IF(New_Finance_Data[[#This Row],[ Sales ]]>=50000,"Medium","Low")) -> Low | S5: =IF(OR(ISBLANK(New_Finance_Data[[#This Row],[ Sales ]]),ISBLANK(New_Finance_Data[[#This Row],[ Profit ]])),"Missing","OK") -> OK | T5: =TEXT(New_Finance_Data[[#This Row],[Date]],"MMM-YYYY") -> Jun-2014 | U5: =IF(New_Finance_Data[[#This Row],[ Profit ]]>0,"Profit","Loss") -> Profit | V5: =IF(New_Finance_Data[[#This Row],[ Sales ]]>=50000,"High Sales","Low Sales") -> Low Sales | W5: =ISNUMBER(New_Finance_Data[[#This Row],[Date]]) -> TRUE
A6: Midmarket | B6: Mexico | C6: Carretera | D6: None | E6: 2470 | F6: 3 | G6: 15 | H6: 37050 | I6: 0 | J6: 37050 | K6: 24700 | L6: 12350 | M6: 41791 | N6: 6 | O6: June | P6: 2014 | Q6: =New_Finance_Data[[#This Row],[ Profit ]]/New_Finance_Data[[#This Row],[ Sales ]] -> 0.33333333 | R6: =IF(New_Finance_Data[[#This Row],[ Sales ]]>=100000,"High",IF(New_Finance_Data[[#This Row],[ Sales ]]>=50000,"Medium","Low")) -> Low | S6: =IF(OR(ISBLANK(New_Finance_Data[[#This Row],[ Sales ]]),ISBLANK(New_Finance_Data[[#This Row],[ Profit ]])),"Missing","OK") -> OK | T6: =TEXT(New_Finance_Data[[#This Row],[Date]],"MMM-YYYY") -> Jun-2014 | U6: =IF(New_Finance_Data[[#This Row],[ Profit ]]>0,"Profit","Loss") -> Profit | V6: =IF(New_Finance_Data[[#This Row],[ Sales ]]>=50000,"High Sales","Low Sales") -> Low Sales | W6: =ISNUMBER(New_Finance_Data[[#This Row],[Date]]) -> TRUE
A7: Government | B7: Germany | C7: Carretera | D7: None | E7: 1513 | F7: 3 | G7: 350 | H7: 529550 | I7: 0 | J7: 529550 | K7: 393380 | L7: 136170 | M7: 41974 | N7: 12 | O7: December | P7: 2014 | Q7: =New_Finance_Data[[#This Row],[ Profit ]]/New_Finance_Data[[#This Row],[ Sales ]] -> 0.25714286 | R7: =IF(New_Finance_Data[[#This Row],[ Sales ]]>=100000,"High",IF(New_Finance_Data[[#This Row],[ Sales ]]>=50000,"Medium","Low")) -> High | S7: =IF(OR(ISBLANK(New_Finance_Data[[#This Row],[ Sales ]]),ISBLANK(New_Finance_Data[[#This Row],[ Profit ]])),"Missing","OK") -> OK | T7: =TEXT(New_Finance_Data[[#This Row],[Date]],"MMM-YYYY") -> Dec-2014 | U7: =IF(New_Finance_Data[[#This Row],[ Profit ]]>0,"Profit","Loss") -> Profit | V7: =IF(New_Finance_Data[[#This Row],[ Sales ]]>=50000,"High Sales","Low Sales") -> High Sales | W7: =ISNUMBER(New_Finance_Data[[#This Row],[Date]]) -> TRUE
A8: Midmarket | B8: Germany | C8: Montana | D8: None | E8: 921 | F8: 5 | G8: 15 | H8: 13815 | I8: 0 | J8: 13815 | K8: 9210 | L8: 4605 | M8: 41699 | N8: 3 | O8: March | P8: 2014 | Q8: =New_Finance_Data[[#This Row],[ Profit ]]/New_Finance_Data[[#This Row],[ Sales ]] -> 0.33333333 | R8: =IF(New_Finance_Data[[#This Row],[ Sales ]]>=100000,"High",IF(New_Finance_Data[[#This Row],[ Sales ]]>=50000,"Medium","Low")) -> Low | S8: =IF(OR(ISBLANK(New_Finance_Data[[#This Row],[ Sales ]]),ISBLANK(New_Finance_Data[[#This Row],[ Profit ]])),"Missing","OK") -> OK | T8: =TEXT(New_Finance_Data[[#This Row],[Date]],"MMM-YYYY") -> Mar-2014 | U8: =IF(New_Finance_Data[[#This Row],[ Profit ]]>0,"Profit","Loss") -> Profit | V8: =IF(New_Finance_Data[[#This Row],[ Sales ]]>=50000,"High Sales","Low Sales") -> Low Sales | W8: =ISNUMBER(New_Finance_Data[[#This Row],[Date]]) -> TRUE
A9: Channel Partners | B9: Canada | C9: Montana | D9: None | E9: 2518 | F9: 5 | G9: 12 | H9: 30216 | I9: 0 | J9: 30216 | K9: 7554 | L9: 22662 | M9: 41791 | N9: 6 | O9: June | P9: 2014 | Q9: =New_Finance_Data[[#This Row],[ Profit ]]/New_Finance_Data[[#This Row],[ Sales ]] -> 0.75 | R9: =IF(New_Finance_Data[[#This Row],[ Sales ]]>=100000,"High",IF(New_Finance_Data[[#This Row],[ Sales ]]>=50000,"Medium","Low")) -> Low | S9: =IF(OR(ISBLANK(New_Finance_Data[[#This Row],[ Sales ]]),ISBLANK(New_Finance_Data[[#This Row],[ Profit ]])),"Missing","OK") -> OK | T9: =TEXT(New_Finance_Data[[#This Row],[Date]],"MMM-YYYY") -> Jun-2014 | U9: =IF(New_Finance_Data[[#This Row],[ Profit ]]>0,"Profit","Loss") -> Profit | V9: =IF(New_Finance_Data[[#This Row],[ Sales ]]>=50000,"High Sales","Low Sales") -> Low Sales | W9: =ISNUMBER(New_Finance_Data[[#This Row],[Date]]) -> TRUE
A10: Government | B10: France | C10: Montana | D10: None | E10: 1899 | F10: 5 | G10: 20 | H10: 37980 | I10: 0 | J10: 37980 | K10: 18990 | L10: 18990 | M10: 41791 | N10: 6 | O10: June | P10: 2014 | Q10: =New_Finance_Data[[#This Row],[ Profit ]]/New_Finance_Data[[#This Row],[ Sales ]] -> 0.5 | R10: =IF(New_Finance_Data[[#This Row],[ Sales ]]>=100000,"High",IF(New_Finance_Data[[#This Row],[ Sales ]]>=50000,"Medium","Low")) -> Low | S10: =IF(OR(ISBLANK(New_Finance_Data[[#This Row],[ Sales ]]),ISBLANK(New_Finance_Data[[#This Row],[ Profit ]])),"Missing","OK") -> OK | T10: =TEXT(New_Finance_Data[[#This Row],[Date]],"MMM-YYYY") -> Jun-2014 | U10: =IF(New_Finance_Data[[#This Row],[ Profit ]]>0,"Profit","Loss") -> Profit | V10: =IF(New_Finance_Data[[#This Row],[ Sales ]]>=50000,"High Sales","Low Sales") -> Low Sales | W10: =ISNUMBER(New_Finance_Data[[#This Row],[Date]]) -> TRUE
A11: Channel Partners | B11: Germany | C11: Montana | D11: None | E11: 1545 | F11: 5 | G11: 12 | H11: 18540 | I11: 0 | J11: 18540 | K11: 4635 | L11: 13905 | M11: 41791 | N11: 6 | O11: June | P11: 2014 | Q11: =New_Finance_Data[[#This Row],[ Profit ]]/New_Finance_Data[[#This Row],[ Sales ]] -> 0.75 | R11: =IF(New_Finance_Data[[#This Row],[ Sales ]]>=100000,"High",IF(New_Finance_Data[[#This Row],[ Sales ]]>=50000,"Medium","Low")) -> Low | S11: =IF(OR(ISBLANK(New_Finance_Data[[#This Row],[ Sales ]]),ISBLANK(New_Finance_Data[[#This Row],[ Profit ]])),"Missing","OK") -> OK | T11: =TEXT(New_Finance_Data[[#This Row],[Date]],"MMM-YYYY") -> Jun-2014 | U11: =IF(New_Finance_Data[[#This Row],[ Profit ]]>0,"Profit","Loss") -> Profit | V11: =IF(New_Finance_Data[[#This Row],[ Sales ]]>=50000,"High Sales","Low Sales") -> Low Sales | W11: =ISNUMBER(New_Finance_Data[[#This Row],[Date]]) -> TRUE
A12: Midmarket | B12: Mexico | C12: Montana | D12: None | E12: 2470 | F12: 5 | G12: 15 | H12: 37050 | I12: 0 | J12: 37050 | K12: 24700 | L12: 12350 | M12: 41791 | N12: 6 | O12: June | P12: 2014 | Q12: =New_Finance_Data[[#This Row],[ Profit ]]/New_Finance_Data[[#This Row],[ Sales ]] -> 0.33333333 | R12: =IF(New_Finance_Data[[#This Row],[ Sales ]]>=100000,"High",IF(New_Finance_Data[[#This Row],[ Sales ]]>=50000,"Medium","Low")) -> Low | S12: =IF(OR(ISBLANK(New_Finance_Data[[#This Row],[ Sales ]]),ISBLANK(New_Finance_Data[[#This Row],[ Profit ]])),"Missing","OK") -> OK | T12: =TEXT(New_Finance_Data[[#This Row],[Date]],"MMM-YYYY") -> Jun-2014 | U12: =IF(New_Finance_Data[[#This Row],[ Profit ]]>0,"Profit","Loss") -> Profit | V12: =IF(New_Finance_Data[[#This Row],[ Sales ]]>=50000,"High Sales","Low Sales") -> Low Sales | W12: =ISNUMBER(New_Finance_Data[[#This Row],[Date]]) -> TRUE
A13: Enterprise | B13: Canada | C13: Montana | D13: None | E13: 2665.5 | F13: 5 | G13: 125 | H13: 333187.5 | I13: 0 | J13: 333187.5 | K13: 319860 | L13: 13327.5 | M13: 41821 | N13: 7 | O13: July | P13: 2014 | Q13: =New_Finance_Data[[#This Row],[ Profit ]]/New_Finance_Data[[#This Row],[ Sales ]] -> 0.04 | R13: =IF(New_Finance_Data[[#This Row],[ Sales ]]>=100000,"High",IF(New_Finance_Data[[#This Row],[ Sales ]]>=50000,"Medium","Low")) -> High | S13: =IF(OR(ISBLANK(New_Finance_Data[[#This Row],[ Sales ]]),ISBLANK(New_Finance_Data[[#This Row],[ Profit ]])),"Missing","OK") -> OK | T13: =TEXT(New_Finance_Data[[#This Row],[Date]],"MMM-YYYY") -> Jul-2014 | U13: =IF(New_Finance_Data[[#This Row],[ Profit ]]>0,"Profit","Loss") -> Profit | V13: =IF(New_Finance_Data[[#This Row],[ Sales ]]>=50000,"High Sales","Low Sales") -> High Sales | W13: =ISNUMBER(New_Finance_Data[[#This Row],[Date]]) -> TRUE
... A701: Channel Partners | B701: United States of America | C701: VTT | D701: High | E701: 1806 | F701: 250 | G701: 12 | H701: 21672 | I701: 3250.8 | J701: 18421.2 | K701: 5418 | L701: 13003.2 | M701: 41760 | N701: 5 | O701: May | P701: 2014 | Q701: =New_Finance_Data[[#This Row],[ Profit ]]/New_Finance_Data[[#This Row],[ Sales ]] -> 0.70588235 | R701: =IF(New_Finance_Data[[#This Row],[ Sales ]]>=100000,"High",IF(New_Finance_Data[[#This Row],[ Sales ]]>=50000,"Medium","Low")) -> Low | S701: =IF(OR(ISBLANK(New_Finance_Data[[#This Row],[ Sales ]]),ISBLANK(New_Finance_Data[[#This Row],[ Profit ]])),"Missing","OK") -> OK | T701: =TEXT(New_Finance_Data[[#This Row],[Date]],"MMM-YYYY") -> May-2014 | U701: =IF(New_Finance_Data[[#This Row],[ Profit ]]>0,"Profit","Loss") -> Profit | V701: =IF(New_Finance_Data[[#This Row],[ Sales ]]>=50000,"High Sales","Low Sales") -> Low Sales | W701: =ISNUMBER(New_Finance_Data[[#This Row],[Date]]) -> TRUE

Sheet Pivot
A3: Sum of Sales | C3: Sum of Profit | E3: Sum of Gross Sales | G3: Sum of Units Sold | I3: Sum of Discounts | K3: Profit Margin | O3: Row Labels | P3: Sum of Profit | Q3: Sum of Sales
A4: 1.1872635e+08 | C4: 16893702 | E4: 1.279316e+08 | G4: 1125806 | I4: 9205248.3 | K4: =C4/A4 -> 0.14229109 | O4: 2013 | P4: 3878464.5 | Q4: 26415256
O5: Sep | P5: 763603.03 | Q5: 4484000
O6: Oct | P6: 1657795.1 | Q6: 9295611.1
A7: Row Labels | B7: Sum of Sales | E7: Row Labels | F7: Sum of Profit | I7: Row Labels | J7: Sum of Sales | M7: Row Labels | N7: Sum of Sales | O7: Nov | P7: 765502.3 | Q7: 7267203.3
A8: 2013 | B8: 26415256 | E8: Canada | F8: 3529228.9 | I8: Channel Partners | J8: 1800593.6 | M8: Amarilla | N8: 17747116 | O8: Dec | P8: 691564.08 | Q8: 5368441.1
A9: Sep | B9: 4484000 | E9: France | F9: 3781020.8 | I9: Midmarket | J9: 2381883.1 | M9: Carretera | N9: 13815308 | O9: 2014 | P9: 13015238 | Q9: 92311095
A10: Oct | B10: 9295611.1 | E10: Germany | F10: 3680388.8 | I10: Enterprise | J10: 19611694 | M10: Montana | N10: 15390802 | O10: Jan | P10: 814028.68 | Q10: 6607761.7
A11: Nov | B11: 7267203.3 | E11: Mexico | F11: 2907523.1 | I11: Small Business | J11: 42427918 | M11: Paseo | N11: 33011144 | O11: Feb | P11: 1148547.4 | Q11: 7297531.4
A12: Dec | B12: 5368441.1 | E12: United States of America | F12: 2995540.6 | I12: Government | J12: 52504261 | M12: Velo | N12: 18250059 | O12: Mar | P12: 669866.87 | Q12: 5586859.9
A13: 2014 | B13: 92311095 | E13: Grand Total | F13: 16893702 | I13: Grand Total | J13: 1.1872635e+08 | M13: VTT | N13: 20511921 | O13: Apr | P13: 929984.57 | Q13: 6964775.1
A14: Jan | B14: 6607761.7 | M14: Grand Total | N14: 1.1872635e+08 | O14: May | P14: 828640.06 | Q14: 6210211.1
A15: Feb | B15: 7297531.4 | O15: Jun | P15: 1473753.8 | Q15: 9518893.8
A16: Mar | B16: 5586859.9 | O16: Jul | P16: 923865.67 | Q16: 8102920.2
A17: Apr | B17: 6964775.1 | O17: Aug | P17: 791066.42 | Q17: 5864622.4
A18: May | B18: 6210211.1 | O18: Sep | P18: 1023132.2 | Q18: 6398697.2
A19: Jun | B19: 9518893.8 | O19: Oct | P19: 1781985.9 | Q19: 12375820
A20: Jul | B20: 8102920.2 | I20: Row Labels | J20: Count of Discounts | O20: Nov | P20: 604600.2 | Q20: 5384214.2
A21: Aug | B21: 5864622.4 | I21: High | J21: 245 | O21: Dec | P21: 2025765.9 | Q21: 11998788
A22: Sep | B22: 6398697.2 | I22: Low | J22: 160 | O22: Grand Total | P22: 16893702 | Q22: 1.1872635e+08
A23: Oct | B23: 12375820 | I23: Medium | J23: 242
A24: Nov | B24: 5384214.2 | I24: None | J24: 53
A25: Dec | B25: 11998788 | I25: Grand Total | J25: 700
A26: Grand Total | B26: 1.1872635e+08
I31: Product | J31: Sum of Discounts | K31: Sales | L31: Gross Sales($) | M31: Sum of COGS | N31: Sum of Profit | O31: Units Sold | P31: Profit Margin
I32: Amarilla | J32: 1290163.4 | K32: 17747116 | L32: 19037280 | M32: 14933012 | N32: 2814104 | O32: 155315 | P32: =GETPIVOTDATA("Sum of Profit ",$I$31," Product "," Amarilla ")/GETPIVOTDATA("Sales ",$I$31," Product "," Amarilla ") -> 0.15856684
I33: Carretera | J33: 1122212.6 | K33: 13815308 | L33: 14937520 | M33: 11988503 | N33: 1826804.9 | O33: 146846 | P33: =GETPIVOTDATA("Sum of Profit ",$I$31," Product "," Carretera ")/GETPIVOTDATA("Sales ",$I$31," Product "," Carretera ") -> 0.13223049
I34: Montana | J34: 1159032.6 | K34: 15390802 | L34: 16549834 | M34: 13276047 | N34: 2114754.9 | O34: 154198 | P34: =GETPIVOTDATA("Sum of Profit ",$I$31," Product "," Montana ")/GETPIVOTDATA("Sales ",$I$31," Product "," Montana ") -> 0.13740381
I35: Paseo | J35: 2600518.1 | K35: 33011144 | L35: 35611662 | M35: 28213706 | N35: 4797437.9 | O35: 338239.5 | P35: =GETPIVOTDATA("Units Sold ",$I$31," Product "," Paseo ")/GETPIVOTDATA("Sales ",$I$31," Product "," Paseo ") -> 0.010246222
I36: Velo | J36: 1576709 | K36: 18250059 | L36: 19826768 | M36: 15944067 | N36: 2305992.5 | O36: 162424.5 | P36: =GETPIVOTDATA("Sum of Profit ",$I$31," Product "," Velo ")/GETPIVOTDATA("Sales ",$I$31," Product "," Velo ") -> 0.12635534
I37: VTT | J37: 1456612.5 | K37: 20511921 | L37: 21968534 | M37: 17477313 | N37: 3034608 | O37: 168783 | P37: =GETPIVOTDATA("Sum of Profit ",$I$31," Product "," VTT ")/GETPIVOTDATA("Sales ",$I$31," Product "," VTT ") -> 0.14794363

Sheet Helper
A1: Element | B1: HEX
A2: Background | B2: #F8FAFC
A3: KPI Card | B3: #FFFFFF | F3: Profit Margin | I3: Segment | J3: Sales | M3: Saleds
A4: Border | B4: #E5E7EB | F4: =GETPIVOTDATA(" Profit ",Pivot!$C$3)/GETPIVOTDATA(" Sales ",Pivot!$A$3) -> 0.14229109 | I4: Government | J4: =GETPIVOTDATA(" Sales ",Pivot!$I$7,"Segment","Channel Partners") -> 1800593.6 | M4: =GETPIVOTDATA(" Sales ",Pivot!$I$7,"Segment","Channel Partners") -> 1800593.6
A5: Main Title | B5: #0F2D62 | I5: Midmarket | J5: =GETPIVOTDATA(" Sales ",Pivot!$I$7,"Segment","Midmarket") -> 2381883.1
A6: KPI Value | B6: #0B1F44 | I6: Enterprise | J6: =GETPIVOTDATA(" Sales ",Pivot!$I$7,"Segment","Enterprise") -> 19611694
A7: KPI Title | B7: #6B7280 | I7: Small Business | J7: =GETPIVOTDATA(" Sales ",Pivot!$I$7,"Segment","Small Business") -> 42427918
A8: Subtitle | B8: #94A3B8 | I8: Channel Partners | J8: =GETPIVOTDATA(" Sales ",Pivot!$I$7,"Segment","Government") -> 52504261
F11: High | G11: =GETPIVOTDATA(" Discounts ",Pivot!$I$20," Discount Band "," High ") -> 245
F12: Low | G12: =GETPIVOTDATA(" Discounts ",Pivot!$I$20," Discount Band "," Low ") -> 160
F13: Medium | G13: =GETPIVOTDATA(" Discounts ",Pivot!$I$20," Discount Band "," Medium ") -> 242
F14: None | G14: =GETPIVOTDATA(" Discounts ",Pivot!$I$20," Discount Band "," None ") -> 53

Sheet Dashboard
B51: Product | C51: Sales($) | D51: Gross Sales($) | E51: COGS($) | F51: Discounts($) | G51: Profit($) | H51: Profti Margin(%) | I51: Units Sold
B52: =Pivot!I32 -> Amarilla | C52: =GETPIVOTDATA("Sales ",Pivot!$I$32," Product "," Amarilla ") -> 17747116 | D52: =GETPIVOTDATA("Gross Sales($)",Pivot!$I$31," Product "," Amarilla ") -> 19037280 | E52: =GETPIVOTDATA("Sum of COGS ",Pivot!$I$31," Product "," Amarilla ") -> 14933012 | F52: =GETPIVOTDATA("Sum of Discounts ",Pivot!$I$31," Product "," Amarilla ") -> 1290163.4 | G52: =GETPIVOTDATA("Sum of Profit ",Pivot!$I$31," Product "," Amarilla ") -> 2814104 | H52: =Table4[[#This Row],[Profit($)]]/Table4[[#This Row],[Sales($)]] -> 0.15856684 | I52: =GETPIVOTDATA("Units Sold ",Pivot!$I$31," Product "," Amarilla ") -> 155315
B53: =Pivot!I33 -> Carretera | C53: =GETPIVOTDATA("Sales ",Pivot!$I$31," Product "," Carretera ") -> 13815308 | D53: =GETPIVOTDATA("Gross Sales($)",Pivot!$I$31," Product "," Carretera ") -> 14937520 | E53: =GETPIVOTDATA("Sum of COGS ",Pivot!$I$31," Product "," Carretera ") -> 11988503 | F53: =GETPIVOTDATA("Sum of Discounts ",Pivot!$I$31," Product "," Carretera ") -> 1122212.6 | G53: =GETPIVOTDATA("Sum of Profit ",Pivot!$I$31," Product "," Carretera ") -> 1826804.9 | H53: =Table4[[#This Row],[Profit($)]]/Table4[[#This Row],[Sales($)]] -> 0.13223049 | I53: =GETPIVOTDATA("Units Sold ",Pivot!$I$31," Product "," Carretera ") -> 146846
B54: =Pivot!I34 -> Montana | C54: =GETPIVOTDATA("Sales ",Pivot!$I$31," Product "," Montana ") -> 15390802 | D54: =GETPIVOTDATA("Gross Sales($)",Pivot!$I$31," Product "," Montana ") -> 16549834 | E54: =GETPIVOTDATA("Sum of Profit ",Pivot!$I$31," Product "," Montana ") -> 2114754.9 | F54: =GETPIVOTDATA("Sum of Discounts ",Pivot!$I$31," Product "," Montana ") -> 1159032.6 | G54: =GETPIVOTDATA("Sum of Profit ",Pivot!$I$31," Product "," Montana ") -> 2114754.9 | H54: =Table4[[#This Row],[Profit($)]]/Table4[[#This Row],[Sales($)]] -> 0.13740381 | I54: =GETPIVOTDATA("Units Sold ",Pivot!$I$31," Product "," Montana ") -> 154198
B55: =Pivot!I35 -> Paseo | C55: =GETPIVOTDATA("Sales ",Pivot!$I$31," Product "," Paseo ") -> 33011144 | D55: =GETPIVOTDATA("Gross Sales($)",Pivot!$I$31," Product "," Paseo ") -> 35611662 | E55: =GETPIVOTDATA("Sum of COGS ",Pivot!$I$31," Product "," Paseo ") -> 28213706 | F55: =GETPIVOTDATA("Sum of Discounts ",Pivot!$I$31," Product "," Paseo ") -> 2600518.1 | G55: =GETPIVOTDATA("Sum of Profit ",Pivot!$I$31," Product "," Paseo ") -> 4797437.9 | H55: =Table4[[#This Row],[Profit($)]]/Table4[[#This Row],[Sales($)]] -> 0.14532783 | I55: =GETPIVOTDATA("Units Sold ",Pivot!$I$31," Product "," Paseo ") -> 338239.5
B56: =Pivot!I36 -> Velo | C56: =GETPIVOTDATA("Sales ",Pivot!$I$31," Product "," Velo ") -> 18250059 | D56: =GETPIVOTDATA("Gross Sales($)",Pivot!$I$31," Product "," Velo ") -> 19826768 | E56: =GETPIVOTDATA("Sum of COGS ",Pivot!$I$31," Product "," Velo ") -> 15944067 | F56: =GETPIVOTDATA("Sum of Discounts ",Pivot!$I$31," Product "," Velo ") -> 1576709 | G56: =GETPIVOTDATA("Sum of Profit ",Pivot!$I$31," Product "," Velo ") -> 2305992.5 | H56: =Table4[[#This Row],[Profit($)]]/Table4[[#This Row],[Sales($)]] -> 0.12635534 | I56: =GETPIVOTDATA("Units Sold ",Pivot!$I$31," Product "," Velo ") -> 162424.5
B57: =Pivot!I37 -> VTT | C57: =GETPIVOTDATA("Sales ",Pivot!$I$31," Product "," VTT ") -> 20511921 | D57: =GETPIVOTDATA("Gross Sales($)",Pivot!$I$31," Product "," VTT ") -> 21968534 | E57: =GETPIVOTDATA("Sum of COGS ",Pivot!$I$31," Product "," VTT ") -> 17477313 | F57: =GETPIVOTDATA("Sum of Discounts ",Pivot!$I$31," Product "," VTT ") -> 1456612.5 | G57: =GETPIVOTDATA("Sum of Profit ",Pivot!$I$31," Product "," VTT ") -> 3034608 | H57: =Table4[[#This Row],[Profit($)]]/Table4[[#This Row],[Sales($)]] -> 0.14794363 | I57: =GETPIVOTDATA("Units Sold ",Pivot!$I$31," Product "," VTT ") -> 168783
